{
    "-9125904828142384003": {
        "artist": "Sam Cooke",
        "track": "Nothing Can Change This Love"
    },
    "-9033096278402542437": {
        "artist": "Kim Carnes",
        "track": "Bette Davis Eyes"
    },
    "-9016053491523212617": {
        "artist": "Brother Culture, Derrick Sound",
        "track": "Fling a Fyah"
    },
    "-8995222996475145787": {
        "artist": "Tre allegri ragazzi morti",
        "track": "Il mondo prima"
    },
    "-8954673138297995171": {
        "artist": "Marcello Colasurdo",
        "track": "Ritarantella"
    },
    "-8946251429173771565": {
        "artist": "Genesis",
        "track": "I Can't Dance"
    },
    "-8859126665764099152": {
        "artist": "Scott Bradlee's Postmodern Jukebox",
        "track": "Hey Ya!"
    },
    "-8856727697417858882": {
        "artist": "Sly & The Family Stone",
        "track": "If You Want Me To Stay"
    },
    "-8766012832818421166": {
        "artist": "Angel Bat Dawid",
        "track": "Transition East"
    },
    "-8685813335659037832": {
        "artist": "Neil Young",
        "track": "Rockin' in the Free World"
    },
    "-8617477211525293055": {
        "artist": "Hall & Oates",
        "track": "Maneater"
    },
    "-8570732379974897890": {
        "artist": "Black Sabbath",
        "track": "Iron Man"
    },
    "-8556604952644161052": {
        "artist": "America",
        "track": "A Horse With No Name"
    },
    "-8498019406902367137": {
        "artist": "Elton John",
        "track": "Saturday Night’s Alright (For Fighting)"
    },
    "-8496780146823210439": {
        "artist": "Little Jimmy Dickens",
        "track": "Rock Me"
    },
    "-8474983943303912600": {
        "artist": "2Pac",
        "track": "Picture Me Rollin' (ft. Danny Boy, CPO, Big Syke)"
    },
    "-8444686428511598230": {
        "artist": "Little Pieces of Marmelade",
        "track": "One Cup of Happiness"
    },
    "-8390001444937550441": {
        "artist": "Alain Goraguer",
        "track": "06 - You and the Night and the Music"
    },
    "-8275676578227114505": {
        "artist": "Emre Gültekin & Vardan Hovanissian",
        "track": "Daglar"
    },
    "-8146043930611579620": {
        "artist": "Radiodervish",
        "track": "Bombay Salam (Pop Version)"
    },
    "-8051380716375875615": {
        "artist": "Ice Cube",
        "track": "It Was A Good Day"
    },
    "-8025933322962011021": {
        "artist": "Sangennarobar",
        "track": "Dove Sta Zazà (Sangennarobar Special Edition)"
    },
    "-8020577362428694764": {
        "artist": "Dr. Dre, Snoop Doggy Dogg",
        "track": "Nuthin' But A 'G' Thang"
    },
    "-8000824990619956550": {
        "artist": "Legendary Pink Dots",
        "track": "A Feathered Friend"
    },
    "-7995211881967672847": {
        "artist": "Sangennarobar",
        "track": "On y va (Sangennarobar remix)"
    },
    "-7885760103204397995": {
        "artist": "Creedence Clearwater Revival",
        "track": "Have You Ever Seen the Rain"
    },
    "-7866672455805591793": {
        "artist": "Manitoba",
        "track": "La Domenica"
    },
    "-7820991918807192017": {
        "artist": "Vergo",
        "track": "Bomba"
    },
    "-7820129817201854883": {
        "artist": "Marilyn Manson",
        "track": "The Beautiful People"
    },
    "-7667831194153839336": {
        "artist": "Brother Culture, Radikal Vibration",
        "track": "Create & Happen"
    },
    "-7630673957459565351": {
        "artist": "Ministri",
        "track": "Comunque"
    },
    "-7590401715662949617": {
        "artist": "Pineapple StormTV",
        "track": "Poesia Acústica 10: Recomeçar"
    },
    "-7567411496838746404": {
        "artist": "Radiodervish",
        "track": "Taci, il nemico t'ascolta"
    },
    "-7545595589491204849": {
        "artist": "Linkin Park",
        "track": "One Step Closer"
    },
    "-7514331911441943261": {
        "artist": "Benjamin Lew",
        "track": "Face A Ce Qui Se Derobe"
    },
    "-7469014908598811857": {
        "artist": "Extreme",
        "track": "More Than Words"
    },
    "-7432731118192028449": {
        "artist": "DakhaBrakha",
        "track": "Dostochka"
    },
    "-7410356527341865464": {
        "artist": "Litfiba",
        "track": "Proibito"
    },
    "-7375357897579321002": {
        "artist": "Young Gun Silver Fox",
        "track": "Kids"
    },
    "-7362669201631544562": {
        "artist": "Adelitas Way",
        "track": "Cage The Beast"
    },
    "-7247236841054898512": {
        "artist": "Bush",
        "track": "Cold Contagious"
    },
    "-7245169930367017875": {
        "artist": "Dire Straits",
        "track": "Sultans of Swing"
    },
    "-7239985599799546198": {
        "artist": "Bon Jovi",
        "track": "It's My Life"
    },
    "-7237600667263078338": {
        "artist": "Eric Clapton",
        "track": "Cocaine"
    },
    "-7118659899993118885": {
        "artist": "Tears for Fears",
        "track": "Sowing The Seeds Of Love"
    },
    "-7010235674473137346": {
        "artist": "dumama + kechou",
        "track": "for madala"
    },
    "-7001235051816662118": {
        "artist": "James Brown",
        "track": "That's Life"
    },
    "-6981951487698548112": {
        "artist": "SCHROOTHOOP",
        "track": "Mammoettanker"
    },
    "-6966684654843521174": {
        "artist": "The Four Tops",
        "track": "I Can't Help Myself (Sugar Pie, Honey Bunch)"
    },
    "-6948740572236423742": {
        "artist": "Toni Braxton",
        "track": "Gotta Move On"
    },
    "-6919715621007564399": {
        "artist": "dumama + kechou",
        "track": "wessi walking mama"
    },
    "-6859783184838049768": {
        "artist": "The Many",
        "track": "Aardvarck - Start"
    },
    "-6857100512276446706": {
        "artist": "Supertramp",
        "track": "The Logical Song"
    },
    "-6826549486866312559": {
        "artist": "Melancholia",
        "track": "Léon"
    },
    "-6752192841013973255": {
        "artist": "The Pretty Reckless",
        "track": "Make Me Wanna Die"
    },
    "-6644962563303808954": {
        "artist": "Slipknot",
        "track": "Vermilion, Pt. 2"
    },
    "-6571216049359377397": {
        "artist": "Eagles",
        "track": "Life in the Fast Lane"
    },
    "-6523439635332419296": {
        "artist": "AC/DC",
        "track": "Jailbreak"
    },
    "-6504331738082911089": {
        "artist": "Don Cherry",
        "track": "Luna Turca"
    },
    "-6495935846078140810": {
        "artist": "Pantera",
        "track": "Domination"
    },
    "-6426834361882546105": {
        "artist": "Cream",
        "track": "Sunshine of Your Love"
    },
    "-6354241998749064728": {
        "artist": "Max Gazzè",
        "track": "Teresa"
    },
    "-6353980403935575846": {
        "artist": "Metallica",
        "track": "Enter Sandman"
    },
    "-6320647822151170219": {
        "artist": "Bon Jovi",
        "track": "Never Say Goodbye"
    },
    "-6272421860514967698": {
        "artist": "Matteo Re",
        "track": "Playlist di Natale"
    },
    "-6254710960112103046": {
        "artist": "Emre Gültekin & Vardan Hovanissian",
        "track": "Hrant Dink"
    },
    "-6249927063456416685": {
        "artist": "James Brown",
        "track": "It's a Man's Man's Man's World"
    },
    "-6214994564268325755": {
        "artist": "Sangennarobar",
        "track": "Tarantella del gargano (Sangennarobar special edition)"
    },
    "-6202509638849598779": {
        "artist": "Ten Years After",
        "track": "I'd Love to Change the World"
    },
    "-6186004027377025337": {
        "artist": "The James Hunter Six",
        "track": "I Can Change Your Mind"
    },
    "-6174466799506262978": {
        "artist": "Dust-To-Digital",
        "track": "Zacamandú (Mexico)"
    },
    "-6151433684364677967": {
        "artist": "Juri Camisasca",
        "track": "La musica muore"
    },
    "-6146333662451195630": {
        "artist": "Daniele Sepe Und Rote Jazz Fraktion",
        "track": "Zut/a/traverso"
    },
    "-6087606202840398229": {
        "artist": "Benjamin Lew",
        "track": "Qu’Il Fasse Nuit"
    },
    "-6078701560074271205": {
        "artist": "Emre Gültekin & Vardan Hovanissian",
        "track": "Ramazan Güngör"
    },
    "-6018591217617121496": {
        "artist": "K.óla",
        "track": "Plastprinsessan vaknar"
    },
    "-6013623365061645013": {
        "artist": "Radiodervish",
        "track": "Centro del mundo"
    },
    "-5997230710305075072": {
        "artist": "dumama + kechou",
        "track": "mother time"
    },
    "-5993698863253030335": {
        "artist": "Vinicio Capossela",
        "track": "Lettere di soldati"
    },
    "-5966631559864011837": {
        "artist": "Radiodervish",
        "track": "L' esigenza"
    },
    "-5943216641708598279": {
        "artist": "Llorca",
        "track": "I Cry"
    },
    "-5843622743620948579": {
        "artist": "99 Posse",
        "track": "Sfumature"
    },
    "-5777118486958137180": {
        "artist": "dumama + kechou",
        "track": "uveni"
    },
    "-5762509941260012099": {
        "artist": "Bluvertigo",
        "track": "l'assenzio ( the power of nothing)"
    },
    "-5762097465850932032": {
        "artist": "Bon Jovi",
        "track": "You Give Love a Bad Name"
    },
    "-5684948201867547666": {
        "artist": "Metallica",
        "track": "The Unforgiven"
    },
    "-5630873466733193761": {
        "artist": "SCHROOTHOOP",
        "track": "Rostfrei"
    },
    "-5626796040112284829": {
        "artist": "Emre Gültekin & Vardan Hovanissian",
        "track": "Sevdali Günler"
    },
    "-5624708464070378523": {
        "artist": "ZZ Top",
        "track": "La Grange"
    },
    "-5572371348780151642": {
        "artist": "Marcello Colasurdo",
        "track": "Le Fiabe Del Bosco: A)Richiamo Dei Grifoni; B)Auciello Grifone; C)La Sposina"
    },
    "-5522373657825350922": {
        "artist": "Daniele Sepe Und Rote Jazz Fraktion",
        "track": "Il mondo visto dalla panchina"
    },
    "-5521444485937974267": {
        "artist": "Bon Jovi",
        "track": "Wanted Dead or Alive"
    },
    "-5514975877318627402": {
        "artist": "Benjamin Lew",
        "track": "Hommes Assis Devant Un Mur Chaulé"
    },
    "-5318811538228406095": {
        "artist": "Bon Jovi",
        "track": "These Days"
    },
    "-5251416767820943220": {
        "artist": "Eazy-E",
        "track": "Real Muthaphuckkin G's"
    },
    "-5241422174509035275": {
        "artist": "Afterhours",
        "track": "Non è per sempre"
    },
    "-5219161090974387457": {
        "artist": "Christopher Cross",
        "track": "Ride Like the Wind"
    },
    "-5215886375653416490": {
        "artist": "DakhaBrakha",
        "track": "Lado"
    },
    "-5215393194021624982": {
        "artist": "Brother Culture, Radikal Vibration",
        "track": "Brexit"
    },
    "-5207599172677970860": {
        "artist": "Mitsoura",
        "track": "Ederlezi"
    },
    "-5155678782804966312": {
        "artist": "Stevie Nicks",
        "track": "Edge of Seventeen"
    },
    "-5062638124411976169": {
        "artist": "Emre Gültekin & Vardan Hovanissian",
        "track": "Madenciler"
    },
    "-5057855578921846868": {
        "artist": "Don Cherry",
        "track": "Flute Song"
    },
    "-5041167215970409308": {
        "artist": "Afterhours",
        "track": "Ossigeno"
    },
    "-5034313854571793753": {
        "artist": "Caparezza",
        "track": "Mica Van Gogh"
    },
    "-4973270746923896042": {
        "artist": "James Brown",
        "track": "I'll Go Crazy"
    },
    "-4961850462821335754": {
        "artist": "Radiodervish",
        "track": "Acid Baby"
    },
    "-4873497696550961011": {
        "artist": "Radiodervish",
        "track": "Erevan"
    },
    "-4867854331248892943": {
        "artist": "Brother Culture, Nello B, Radikal Vibration",
        "track": "Stepping Up"
    },
    "-4821750610378812528": {
        "artist": "CCCP – Fedeli Alla Linea",
        "track": "Annarella"
    },
    "-4812210335012883622": {
        "artist": "Neffa",
        "track": "Cambierà"
    },
    "-4759251623348843987": {
        "artist": "Talk Talk",
        "track": "Life's What You Make It"
    },
    "-4731166154544313990": {
        "artist": "DakhaBrakha",
        "track": "Khyma"
    },
    "-4696093857739852422": {
        "artist": "Alain Goraguer",
        "track": "10 - Prelude to a Kiss"
    },
    "-4628357378234059535": {
        "artist": "Deftones",
        "track": "My Own Summer (Shove It)"
    },
    "-4610071515518964669": {
        "artist": "Pink Floyd",
        "track": "Money"
    },
    "-4589679852021708140": {
        "artist": "DJ Quik",
        "track": "Pitch in on a Party"
    },
    "-4579005746199476274": {
        "artist": "Bon Jovi",
        "track": "Have A Nice Day"
    },
    "-4573524633582571003": {
        "artist": "CCCP – Fedeli Alla Linea",
        "track": "Curami"
    },
    "-4536856731141714872": {
        "artist": "Die Antwoord",
        "track": "DntTakeMe4aPoes"
    },
    "-4481607916670756238": {
        "artist": "Radiodervish",
        "track": "Bombay Salam"
    },
    "-4479760104084108520": {
        "artist": "Vulfpeck",
        "track": "LAX (feat. Joey Dosik)"
    },
    "-4443344686229636894": {
        "artist": "Radiodervish",
        "track": "Gaza"
    },
    "-4312896536663490424": {
        "artist": "James Brown",
        "track": "Think"
    },
    "-4288279090618250402": {
        "artist": "Anderson .Paak",
        "track": "JEWELZ"
    },
    "-4203299288226376279": {
        "artist": "Mitsoura",
        "track": "Iboly (Lumaki Agor Mix)"
    },
    "-4198087814981523712": {
        "artist": "Dean & Britta",
        "track": "Happy Xmas (War is Over)"
    },
    "-4117513155775523809": {
        "artist": "Bootsy Collins",
        "track": "I'd Rather Be With You"
    },
    "-4068640981530084633": {
        "artist": "Metallica",
        "track": "Whiskey in the Jar"
    },
    "-4059459305102285032": {
        "artist": "Subsonica",
        "track": "Tutti I Miei Sbagli"
    },
    "-4044945303831633710": {
        "artist": "Casadilego",
        "track": "VITTORIA"
    },
    "-3998615460833397343": {
        "artist": "Franco Battiato",
        "track": "La Convenzione"
    },
    "-3993451252960536594": {
        "artist": "Snoop Dogg",
        "track": "Who Am I (What's My Name)?"
    },
    "-3935155090007141628": {
        "artist": "Pantera",
        "track": "Heresy"
    },
    "-3929748783759151488": {
        "artist": "Bon Jovi",
        "track": "Keep the Faith"
    },
    "-3887950751608610402": {
        "artist": "James Brown",
        "track": "Papa's Got A Brand New Bag"
    },
    "-3885927186066048709": {
        "artist": "Pantera",
        "track": "Shattered"
    },
    "-3868107723216854769": {
        "artist": "Daniele Sepe Und Rote Jazz Fraktion",
        "track": "Ever green"
    },
    "-3864701852603142071": {
        "artist": "Don Cherry",
        "track": "Koye"
    },
    "-3787388086126108996": {
        "artist": "Iron Maiden",
        "track": "Wasting Love"
    },
    "-3774292169354165051": {
        "artist": "Creedence Clearwater Revival",
        "track": "Run Through the Jungle"
    },
    "-3728991944993906890": {
        "artist": "Nik West",
        "track": "Catch Me If You Can"
    },
    "-3724781542211941561": {
        "artist": "James Brown",
        "track": "It's A Man's, Man's, Man's World"
    },
    "-3697932149030564726": {
        "artist": "James Brown",
        "track": "The Christmas Song"
    },
    "-3693441672148675959": {
        "artist": "Santi",
        "track": "Morrison"
    },
    "-3641695331224768453": {
        "artist": "Funkadelic",
        "track": "One Nation Under a Groove"
    },
    "-3638978765434943972": {
        "artist": "Dub Shepherds",
        "track": "Bella Version"
    },
    "-3584293710357126849": {
        "artist": "Slade",
        "track": "Cum On Feel The Noize"
    },
    "-3584039563164467420": {
        "artist": "James Brown",
        "track": "Please, Please, Please"
    },
    "-3530512152821687219": {
        "artist": "Brother Culture, Radikal Vibration",
        "track": "Clear My Name"
    },
    "-3511327689383157712": {
        "artist": "Valotihkuu & Dynastor",
        "track": "Creature Comforts"
    },
    "-3468617672825287222": {
        "artist": "Mitsoura",
        "track": "Kurjah"
    },
    "-3361903824086778066": {
        "artist": "Steve Miller Band",
        "track": "The Joker"
    },
    "-3327592305471906310": {
        "artist": "Radiodervish",
        "track": "Acustico"
    },
    "-3309803810233589019": {
        "artist": "Afterhours",
        "track": "Ci Sono Molti Modi"
    },
    "-3296806036463454709": {
        "artist": "hello",
        "track": "New York Groove"
    },
    "-3263201620807492884": {
        "artist": "Chris Rea",
        "track": "The Road To Hell Part 2"
    },
    "-3255385167326728890": {
        "artist": "Captain Sensible",
        "track": "Wot"
    },
    "-3253499316517269860": {
        "artist": "James Brown",
        "track": "The Boss"
    },
    "-3247431904273489074": {
        "artist": "Nate Wooley",
        "track": "Seven Storey Mountain VI"
    },
    "-3193837375293354249": {
        "artist": "Led Zeppelin",
        "track": "Since I've Been Loving You"
    },
    "-3148271095893630993": {
        "artist": "T. Rex",
        "track": "20th Century Boy"
    },
    "-3139186450866754986": {
        "artist": "Pantera",
        "track": "Cowboys from Hell"
    },
    "-3138951309831993880": {
        "artist": "Vasco Rossi",
        "track": "Gli Angeli"
    },
    "-3119604189759512641": {
        "artist": "Benjamin Lew",
        "track": "Moments"
    },
    "-3104816115965641275": {
        "artist": "Metallica",
        "track": "Nothing Else Matters"
    },
    "-3060475572814505634": {
        "artist": "Alain Goraguer",
        "track": "05 - Stella By Starlight"
    },
    "-3056292945093405304": {
        "artist": "Ledisi",
        "track": "What Kinda Love Is That (feat. Cory Henry)"
    },
    "-3054421497377194428": {
        "artist": "Hall & Oates",
        "track": "Rich Girl"
    },
    "-3052399311798442604": {
        "artist": "Daniele Sepe Und Rote Jazz Fraktion",
        "track": "Bianco & Nero"
    },
    "-3027766830481499590": {
        "artist": "Benjamin Lew",
        "track": "The Wheel"
    },
    "-3006448766451421646": {
        "artist": "Ice Cube",
        "track": "No Vaseline"
    },
    "-2995426634669188704": {
        "artist": "Toto",
        "track": "Africa"
    },
    "-2991899292601524709": {
        "artist": "Mitsoura",
        "track": "Kelushka"
    },
    "-2991849868021429636": {
        "artist": "Brother Culture, Radikal Vibration",
        "track": "Battelfield"
    },
    "-2991325787713637830": {
        "artist": "Benjamin Lew",
        "track": "Little Birds Sit On Your Shoulder"
    },
    "-2986387330010402944": {
        "artist": "Lee Fields  The Expressions",
        "track": "Regenerate"
    },
    "-2976882870031864566": {
        "artist": "Grandbruit",
        "track": "Oratoire 1"
    },
    "-2924836864952099323": {
        "artist": "Alain Goraguer",
        "track": "15 - L 'Homme et l'Enfant"
    },
    "-2850751708136283696": {
        "artist": "Bon Jovi",
        "track": "I'll Be There For You"
    },
    "-2835973248092968225": {
        "artist": "Ten Years After",
        "track": "I'm going home"
    },
    "-2826250940447638256": {
        "artist": "Parliament",
        "track": "Flashlight"
    },
    "-2821552021406575947": {
        "artist": "Brother Culture, Derrick Sound",
        "track": "Rootsman"
    },
    "-2807218391646983723": {
        "artist": "Franco Battiato",
        "track": "Stranizza d'ammuri"
    },
    "-2717318308450565986": {
        "artist": "Juri Camisasca",
        "track": "Himalaya"
    },
    "-2710958039793947808": {
        "artist": "Vasco Brondi",
        "track": "Mistica"
    },
    "-2693692793770368858": {
        "artist": "Alain Goraguer",
        "track": "04 - It's Easy to Remember"
    },
    "-2631419342083503125": {
        "artist": "Tha Dogg Pound",
        "track": "Big Pimpin'"
    },
    "-2607760852321286315": {
        "artist": "The Rolling Stones",
        "track": "Paint It Black"
    },
    "-2590902811079261753": {
        "artist": "Brother Culture, Radikal Vibration",
        "track": "New Love"
    },
    "-2586547450338270738": {
        "artist": "Marcello Colasurdo",
        "track": "Amore Luntano"
    },
    "-2554540549422994474": {
        "artist": "Radiodervish",
        "track": "Ya le temps"
    },
    "-2538924101151443866": {
        "artist": "Sumac Dub",
        "track": "Aloe"
    },
    "-2476288163718503630": {
        "artist": "Vinicio Capossela",
        "track": "Sante nicola"
    },
    "-2464615377853020701": {
        "artist": "Sangennarobar",
        "track": "Tammurriata giuglianese (Sangennarobar special edition)"
    },
    "-2414546422555201242": {
        "artist": "Jimi Hendrix",
        "track": "Purple Haze"
    },
    "-2380717507911888007": {
        "artist": "Blue Phelix",
        "track": "South Dakota"
    },
    "-2320398594530049665": {
        "artist": "Khalid",
        "track": "Shot Down"
    },
    "-2288840699553709894": {
        "artist": "David Bowie",
        "track": "Ziggy Stardust"
    },
    "-2212220816727697848": {
        "artist": "Baustelle",
        "track": "Un romantico a Milano"
    },
    "-2207918821080303145": {
        "artist": "N.A.I.P.",
        "track": "Attenti al Loop"
    },
    "-2174525211810022940": {
        "artist": "Radiodervish",
        "track": "Secret Life"
    },
    "-2078129935928729849": {
        "artist": "Madonna",
        "track": "Material Girl"
    },
    "-2076572172990190788": {
        "artist": "James Brown",
        "track": "Merry Christmas, I Love You"
    },
    "-2014587864318254229": {
        "artist": "Alain Goraguer",
        "track": "03 - Demain Je Dors Jusqu'à MIDI"
    },
    "-2011189307894936201": {
        "artist": "Rammstein",
        "track": "Du Riechst So Gut"
    },
    "-1957594782296225390": {
        "artist": "Sumac Dub",
        "track": "Titania"
    },
    "-1941585340643380765": {
        "artist": "Emre Gültekin & Vardan Hovanissian",
        "track": "Bingyol"
    },
    "-1934718148376512817": {
        "artist": "Monophonics",
        "track": "It's Only Us"
    },
    "-1926009689457917098": {
        "artist": "Vinicio Capossela",
        "track": "Si è spento il sole"
    },
    "-1924646638692516569": {
        "artist": "Gary Hoey",
        "track": "Boxcar Blues"
    },
    "-1908916159377691021": {
        "artist": "Vinicio Capossela",
        "track": "Non C'e'Disaccordo Nel Cielo"
    },
    "-1776858649906910866": {
        "artist": "AC/DC",
        "track": "T.N.T."
    },
    "-1748864309087948146": {
        "artist": "Metallica",
        "track": "Sad but True"
    },
    "-1664201040770050210": {
        "artist": "Daniele Sepe Und Rote Jazz Fraktion",
        "track": "Napoli centrale"
    },
    "-1658956676932676858": {
        "artist": "Vulfpeck",
        "track": "3 on E (feat. Antwaun Stanley)"
    },
    "-1634451618690455320": {
        "artist": "AC/DC",
        "track": "Thunderstruck"
    },
    "-1627279412383919046": {
        "artist": "James Brown",
        "track": "Lost Someone"
    },
    "-1625087287486032350": {
        "artist": "Mario Venuti",
        "track": "Veramente"
    },
    "-1576798163181122991": {
        "artist": "Morgan",
        "track": "Altrove"
    },
    "-1516147812767191612": {
        "artist": "Mitsoura",
        "track": "Tutti Frutti"
    },
    "-1500853517873046360": {
        "artist": "Angel Bat Dawid",
        "track": "No Space Fo Us"
    },
    "-1481014039282212427": {
        "artist": "Yellow Days",
        "track": "The Curse (feat. Mac DeMarco)"
    },
    "-1480098560989199254": {
        "artist": "Jamiroquai",
        "track": "Space Cowboy"
    },
    "-1475911275975652271": {
        "artist": "Don Cherry",
        "track": "A Chi Chi Ou"
    },
    "-1470139159762378440": {
        "artist": "Sangennarobar",
        "track": "Ahi lu core meu (Sangennarobar remix)"
    },
    "-1451004663762649612": {
        "artist": "Franco Battiato",
        "track": "Paranoia"
    },
    "-1410994347269553724": {
        "artist": "James Brown",
        "track": "Try Me"
    },
    "-1392215351825391070": {
        "artist": "James Brown",
        "track": "I Got You (I Feel Good)"
    },
    "-1383472462334112199": {
        "artist": "Bon Jovi",
        "track": "Bed Of Roses"
    },
    "-1360323129454308199": {
        "artist": "Alain Goraguer",
        "track": "09 - What Is This Thing Called Love-"
    },
    "-1354866812821878507": {
        "artist": "Jimi Hendrix",
        "track": "All Along the Watchtower"
    },
    "-1342381204460191974": {
        "artist": "Baustelle",
        "track": "La guerra è finita"
    },
    "-1315164591208327125": {
        "artist": "Billy Idol",
        "track": "Rebel Yell"
    },
    "-1276334818630560468": {
        "artist": "Sangennarobar",
        "track": "Tarantella montemaranese (Sangennarobar special edition)"
    },
    "-1265012328594702291": {
        "artist": "mydrama",
        "track": "Cornici Bianche"
    },
    "-1250573859903477189": {
        "artist": "Foo Fighters",
        "track": "Monkey Wrench"
    },
    "-1229110579907237496": {
        "artist": "Sangennarobar",
        "track": "Cu Ti Lu Dissi (Sangennarobar Special Edition)"
    },
    "-1181508108780389444": {
        "artist": "Aerosmith",
        "track": "Dream On"
    },
    "-1168875364902857121": {
        "artist": "Blue Öyster Cult",
        "track": "(Don't Fear) The Reaper"
    },
    "-1159833675285784878": {
        "artist": "Status Quo",
        "track": "In The Army Now"
    },
    "-1136494278202525850": {
        "artist": "Alain Goraguer",
        "track": "14 - With the Wind and the Rain in Your Hair"
    },
    "-1064824393052126026": {
        "artist": "Midnight Oil",
        "track": "Beds Are Burning"
    },
    "-1050482842518293911": {
        "artist": "The Winchester's",
        "track": "Back in Black"
    },
    "-1033407415255393112": {
        "artist": "James Brown",
        "track": "Santa Claus Go Straight To The Ghetto"
    },
    "-929154204575266814": {
        "artist": "Mitsoura",
        "track": "Kaman Song(Kheimasko Thanesko Beng Mix)"
    },
    "-901512537843824588": {
        "artist": "Blood, Sweat  Tears",
        "track": "Spinning Wheel"
    },
    "-855243974167348036": {
        "artist": "Phil Collins",
        "track": "Another Day in Paradise"
    },
    "-825634509728732065": {
        "artist": "Benjamin Lew",
        "track": "Profondeurs Des Eaux Des Laques"
    },
    "-749181426515842814": {
        "artist": "Korn",
        "track": "Blind"
    },
    "-740290820304980072": {
        "artist": "Sumac Dub",
        "track": "No Man's Dub"
    },
    "-692813992229670503": {
        "artist": "Enrico Turetta",
        "track": "E' la notte di Natale"
    },
    "-662105085986970160": {
        "artist": "Metallica",
        "track": "For Whom the Bell Tolls"
    },
    "-630188182334664125": {
        "artist": "Radiodervish",
        "track": "Due soli"
    },
    "-606603421192450856": {
        "artist": "Marvin Gaye",
        "track": "\"T\" Plays It Cool"
    },
    "-592137412482226813": {
        "artist": "Brother Culture, Radikal Vibration",
        "track": "Right Down"
    },
    "-574433806508032377": {
        "artist": "Sangennarobar",
        "track": "Memoria (feat. Antonio Infantino e Santina Nocerino)"
    },
    "-539223818891111207": {
        "artist": "Brother Culture, Junior Dread, Little Lion Sound, Addis Records",
        "track": "The Control"
    },
    "-410368207325943598": {
        "artist": "James Brown",
        "track": "Bewildered"
    },
    "-376828268929876911": {
        "artist": "Joan Jett and the Blackhearts",
        "track": "I Love Rock 'n' Roll"
    },
    "-311644993153226516": {
        "artist": "Slipknot",
        "track": "Wait and Bleed"
    },
    "-263284244561471245": {
        "artist": "U2",
        "track": "Desire"
    },
    "-199632118971857182": {
        "artist": "Sangennarobar",
        "track": "Dragan's Mescla (Sangennarobar Special Edition)"
    },
    "-139540520505133602": {
        "artist": "Joesef",
        "track": "Glitter (Cover - Recorded at home for Deezer)"
    },
    "-124810667303395828": {
        "artist": "Steppenwolf",
        "track": "Born to Be Wild"
    },
    "-111301868176503290": {
        "artist": "Ensemble Havadià",
        "track": "Finale"
    },
    "-18692872511224101": {
        "artist": "Brunori Sas",
        "track": "Guardia '82"
    },
    "407943331224627": {
        "artist": "Cory Wong",
        "track": "Click Bait (feat. The Hornheads)"
    },
    "69950586014684987": {
        "artist": "Emre Gültekin & Vardan Hovanissian",
        "track": "Mamiki"
    },
    "120148369942793224": {
        "artist": "Son Little",
        "track": "That's the Way"
    },
    "140826508136232689": {
        "artist": "Daniele Sepe Und Rote Jazz Fraktion",
        "track": "Peaches in Regalia"
    },
    "282426529232153795": {
        "artist": "Radiodervish",
        "track": "Radio dervish"
    },
    "286509009671333798": {
        "artist": "Emre Gültekin & Vardan Hovanissian",
        "track": "Getashen"
    },
    "288453832966260528": {
        "artist": "Marcello Colasurdo",
        "track": "Rituali: A)Salita; B)Prova D'Amore; C) Lotta E Contesa"
    },
    "302242845252406412": {
        "artist": "The Allman Brothers Band",
        "track": "Midnight Rider"
    },
    "304292273563867103": {
        "artist": "SCHROOTHOOP",
        "track": "Asbest in Huis"
    },
    "310346397331006727": {
        "artist": "The Cult",
        "track": "Rain"
    },
    "338573665120143674": {
        "artist": "Vinicio Capossela",
        "track": "La Faccia della Terra (with Calexico)"
    },
    "354118327653872047": {
        "artist": "Ben l'Oncle Soul",
        "track": "Two Trees"
    },
    "360479059904188360": {
        "artist": "Yngwie Malmsteen",
        "track": "You Don't Remember, I'll Never Forget"
    },
    "450045647555460825": {
        "artist": "Durand Jones  The Indications",
        "track": "Power To The People"
    },
    "454095162189968832": {
        "artist": "Thee Sinseers",
        "track": "What's His Name"
    },
    "455349420148452796": {
        "artist": "Brother Culture, Addis Records",
        "track": "All That Noise"
    },
    "486282532255929626": {
        "artist": "cmqmartina",
        "track": "Sparami"
    },
    "604034634705235805": {
        "artist": "The Doors",
        "track": "Roadhouse Blues"
    },
    "624628106720624627": {
        "artist": "Radiodervish",
        "track": "Cairo Blues"
    },
    "675754391822258640": {
        "artist": "Mononeon",
        "track": "Invisible"
    },
    "748961769352689967": {
        "artist": "Brother Culture, Radikal Vibration",
        "track": "King Pin"
    },
    "797524195511181808": {
        "artist": "Alain Goraguer",
        "track": "02 - Darn That Dream"
    },
    "885877177229800705": {
        "artist": "Kendrick Lamar",
        "track": "King Kunta"
    },
    "895909281227935055": {
        "artist": "cmqmartina",
        "track": "Serpente"
    },
    "900115344752464502": {
        "artist": "DakhaBrakha",
        "track": "Ya Siv Ne V Toy Litak"
    },
    "974025306444579161": {
        "artist": "Charles-Baptiste",
        "track": "Bled"
    },
    "978535419878685762": {
        "artist": "Audioslave",
        "track": "Like a Stone"
    },
    "1001982823251048520": {
        "artist": "Mitsoura",
        "track": "Pala Late"
    },
    "1067568839484614169": {
        "artist": "Skid Row",
        "track": "Youth Gone Wild"
    },
    "1080274997370709828": {
        "artist": "Modena City Ramblers",
        "track": "In Un Giorno Di Pioggia"
    },
    "1181417891671721779": {
        "artist": "N.A.I.P.",
        "track": "Oh Oh Oh"
    },
    "1215082782311926256": {
        "artist": "Mitsoura",
        "track": "Le Shavore"
    },
    "1234128328023585992": {
        "artist": "Marcello Colasurdo",
        "track": "A suffragio"
    },
    "1239319442987368901": {
        "artist": "The Rolling Stones",
        "track": "Emotional Rescue"
    },
    "1257182257300790981": {
        "artist": "Afterhours",
        "track": "Voglio Una Pelle Splendida"
    },
    "1288821942339006810": {
        "artist": "Emre Gültekin & Vardan Hovanissian",
        "track": "Galissem Durad"
    },
    "1328653906955823100": {
        "artist": "Led Zeppelin",
        "track": "Immigrant Song"
    },
    "1377752306937970367": {
        "artist": "Benjamin Lew",
        "track": "La Magnifique Alcoolique"
    },
    "1387875817866222821": {
        "artist": "Sepultura",
        "track": "Refuse / Resist"
    },
    "1393974284484374752": {
        "artist": "Led Zeppelin",
        "track": "Whole Lotta Love"
    },
    "1413199660123812770": {
        "artist": "Vinicio Capossela",
        "track": "Ovunque proteggi"
    },
    "1427706225340001711": {
        "artist": "Radiodervish",
        "track": "Li Beirut"
    },
    "1427760451786703417": {
        "artist": "Queen",
        "track": "Killer Queen"
    },
    "1455649463864869358": {
        "artist": "Mitsoura",
        "track": "Pundela"
    },
    "1494298455522819362": {
        "artist": "System of a Down",
        "track": "Lonely Day"
    },
    "1558376438489267665": {
        "artist": "Queen",
        "track": "I Want to Break Free"
    },
    "1562568971457946996": {
        "artist": "Radiodervish",
        "track": "Junoon"
    },
    "1572301754743438311": {
        "artist": "Sumac Dub",
        "track": "Sinti Dub"
    },
    "1610649445651735534": {
        "artist": "Benjamin Lew",
        "track": "Ces Personnages"
    },
    "1646533291900411123": {
        "artist": "dumama + kechou",
        "track": "intaka"
    },
    "1751903232630067957": {
        "artist": "dumama + kechou",
        "track": "umzi"
    },
    "1755329231528355077": {
        "artist": "Radiodervish",
        "track": "Bahia"
    },
    "1758828241633103947": {
        "artist": "The Smashing Pumpkins",
        "track": "Cherub Rock"
    },
    "1770218285123728238": {
        "artist": "James Brown",
        "track": "Night Train"
    },
    "1784181837139986565": {
        "artist": "Mötley Crüe",
        "track": "Girls, Girls, Girls"
    },
    "1786795254909999955": {
        "artist": "Paris",
        "track": "Guerrilla Funk"
    },
    "1788733044295723513": {
        "artist": "Kelly Finnigan",
        "track": "No Time To Be Sad"
    },
    "1790301984395423041": {
        "artist": "Havoc  Prodeje",
        "track": "That's the Way it'z Goin' Down"
    },
    "1797505851558508607": {
        "artist": "Paul McCartney",
        "track": "Say Say Say"
    },
    "1819736815422088284": {
        "artist": "James Brown",
        "track": "Christmas Is Coming"
    },
    "1852610030260262967": {
        "artist": "Maze",
        "track": "Color Blind"
    },
    "1882635222682697072": {
        "artist": "Vulfpeck",
        "track": "3 on E"
    },
    "1967555931812943546": {
        "artist": "Juri Camisasca",
        "track": "Il Regno Dell'Eden, 2° Parte"
    },
    "1973440446654907389": {
        "artist": "Brothers Johnson",
        "track": "Strawberry Letter 23"
    },
    "1982156126705708028": {
        "artist": "Emre Gültekin & Vardan Hovanissian",
        "track": "Lusnak Gisher"
    },
    "2002955197188661092": {
        "artist": "Juri Camisasca",
        "track": "Galantuomo"
    },
    "2035471628632025946": {
        "artist": "James Brown",
        "track": "Let's Make Christmas Mean Something This Year"
    },
    "2038099221768400896": {
        "artist": "Daniele Sepe Und Rote Jazz Fraktion",
        "track": "Sintonia N.3 In Mi ♭ Mag  \"Il Gabbiano\""
    },
    "2073813671440210668": {
        "artist": "Emre Gültekin & Vardan Hovanissian",
        "track": "Hampere Hoqis"
    },
    "2102331991227980757": {
        "artist": "Daniele Sepe Und Rote Jazz Fraktion",
        "track": "Sintonia N.4 In Si ♭ Mag  \"L'incendio Di Milano\"\""
    },
    "2175879166487175438": {
        "artist": "O.V. Wright With The Keys",
        "track": "That's How Strong My Love Is"
    },
    "2188113541128474497": {
        "artist": "Ingrid Laubrock",
        "track": "Stir Crazy Episode 39"
    },
    "2209746138802054857": {
        "artist": "Dolly Parton",
        "track": "9 to 5"
    },
    "2217962396676220128": {
        "artist": "Daniele Sepe Und Rote Jazz Fraktion",
        "track": "Sintonia n.5 in DO min \"Epica\""
    },
    "2232717352560978267": {
        "artist": "Foreigner",
        "track": "Urgent"
    },
    "2263573088865644355": {
        "artist": "Sly & The Family Stone",
        "track": "Family Affair"
    },
    "2311909008286859615": {
        "artist": "Nate Dogg",
        "track": "I Got Love"
    },
    "2313108220241916457": {
        "artist": "Brother Culture, Radikal Vibration",
        "track": "My Selecta"
    },
    "2322296611659528024": {
        "artist": "James Brown",
        "track": "Santa Claus, Santa Claus"
    },
    "2542387210579665498": {
        "artist": "Blind",
        "track": "Cuore Nero"
    },
    "2625089241378017494": {
        "artist": "Adam Prescott & Tenor Youthman",
        "track": "A Long Road"
    },
    "2639270417196505849": {
        "artist": "Rage Against the Machine",
        "track": "Guerrilla Radio"
    },
    "2700098166191496762": {
        "artist": "Queen",
        "track": "We Are the Champions"
    },
    "2831763318031849373": {
        "artist": "Deep Purple",
        "track": "Smoke on the Water"
    },
    "2868502423755395962": {
        "artist": "Bob Dylan",
        "track": "Jokerman"
    },
    "2976475150055348671": {
        "artist": "Ice Cube",
        "track": "You Know How We Do It"
    },
    "2988421286961823125": {
        "artist": "Alain Goraguer",
        "track": "07 - Love or Infatuation"
    },
    "3128639125953145241": {
        "artist": "Benjamin Lew",
        "track": "Etendue"
    },
    "3174308041668473717": {
        "artist": "Queen",
        "track": "I Want It All"
    },
    "3265341537314695575": {
        "artist": "Laura Cannell & Kate Ellis",
        "track": "Merrows"
    },
    "3280058805883964795": {
        "artist": "Don Cherry",
        "track": "Om Shanti Om"
    },
    "3342716694309484272": {
        "artist": "Boston",
        "track": "More Than a Feeling"
    },
    "3416554270249813606": {
        "artist": "dumama + kechou",
        "track": "leaving prison"
    },
    "3427664135197928043": {
        "artist": "The Stranglers",
        "track": "Always the Sun"
    },
    "3441061631329029399": {
        "artist": "Daft Punk",
        "track": "Get Lucky (feat. Pharrell Williams  Nile Rodgers)"
    },
    "3489898605090671790": {
        "artist": "Marcello Colasurdo",
        "track": "Voci di venditori ambulanti"
    },
    "3552664670722186377": {
        "artist": "DakhaBrakha",
        "track": "Vynnaya Ya"
    },
    "3572212226501326779": {
        "artist": "SCHROOTHOOP",
        "track": "Plastic Is Burning"
    },
    "3602046107382905419": {
        "artist": "Marillion",
        "track": "Kayleigh"
    },
    "3622125595156606403": {
        "artist": "Sumac Dub",
        "track": "Sys Outro"
    },
    "3670300964873764980": {
        "artist": "Subsonica",
        "track": "Radioestensioni"
    },
    "3718679432908176949": {
        "artist": "Carla Bley",
        "track": "More Brahms"
    },
    "3719822927431046254": {
        "artist": "Sumac Dub",
        "track": "Thunder Shame"
    },
    "3731858389625555883": {
        "artist": "Studio Allstars",
        "track": "The Message - (Tribute to Grand Master Flash  the Furious Five)"
    },
    "3763085216864578252": {
        "artist": "Emre Gültekin & Vardan Hovanissian",
        "track": "Adana"
    },
    "3821062587496883291": {
        "artist": "Paul Simon",
        "track": "You Can Call Me Al"
    },
    "3862548652194625349": {
        "artist": "Sumac Dub",
        "track": "Turtle Blues"
    },
    "3877687365078563322": {
        "artist": "Brother Culture, Radikal Vibration",
        "track": "Final Push"
    },
    "3919956022454703042": {
        "artist": "Chris de Burgh",
        "track": "High on Emotion"
    },
    "4002083114235584482": {
        "artist": "Foo Fighters",
        "track": "All My Life"
    },
    "4026947785822696616": {
        "artist": "Marcello Colasurdo",
        "track": "Peppenella"
    },
    "4059681820021865958": {
        "artist": "Keb' Mo'",
        "track": "I Should’ve"
    },
    "4069501651351194338": {
        "artist": "Yazmin Lacey",
        "track": "Morning Matters"
    },
    "4090866979939496997": {
        "artist": "Above the Law",
        "track": "Black Superman"
    },
    "4127540609931504259": {
        "artist": "Naked Eyes",
        "track": "Promises, Promises"
    },
    "4137701802270983587": {
        "artist": "Afterhours",
        "track": "Bianca"
    },
    "4179095318174190491": {
        "artist": "Sangennarobar",
        "track": "Tarantella mexicana (Sangennarobar special edition)"
    },
    "4191288383191716140": {
        "artist": "Timoria",
        "track": "Sole Spento"
    },
    "4205344291126988438": {
        "artist": "Bon Jovi",
        "track": "Livin' on a Prayer"
    },
    "4299107899796478569": {
        "artist": "UB40",
        "track": "Red Red Wine"
    },
    "4303827525959501408": {
        "artist": "Scorpions",
        "track": "Wind of Change"
    },
    "4349507217777492327": {
        "artist": "Alain Goraguer",
        "track": "11 - British Soup"
    },
    "4379823411986611786": {
        "artist": "Phil Collins",
        "track": "Sussudio"
    },
    "4421837332522116362": {
        "artist": "Ensemble Havadià",
        "track": "Gocce amare"
    },
    "4455630523462052175": {
        "artist": "Santi",
        "track": "Bonsai"
    },
    "4490548713010421904": {
        "artist": "Brother Culture, Derrick Sound",
        "track": "12 Lights"
    },
    "4556365999874382532": {
        "artist": "Radiodervish",
        "track": "New Partisan"
    },
    "4603483025337090438": {
        "artist": "Radiodervish",
        "track": "L' Esigenza (pop version)"
    },
    "4622210055227989993": {
        "artist": "Radiodervish",
        "track": "Habibi"
    },
    "4623694743877834542": {
        "artist": "Cleo Sol",
        "track": "Rose in the Dark"
    },
    "4701185907659461308": {
        "artist": "Ozzy Osbourne",
        "track": "Crazy Train"
    },
    "4719232796353997714": {
        "artist": "Black Pumas",
        "track": "Colors"
    },
    "4742277073993887699": {
        "artist": "Alain Goraguer",
        "track": "13 - Les Lavandières du Portugal"
    },
    "4758001443096087797": {
        "artist": "Brother Culture",
        "track": "Victim"
    },
    "4759625433141553314": {
        "artist": "James Brown",
        "track": "Please Come Home For Christmas"
    },
    "4763791330997976045": {
        "artist": "Joy Denalane",
        "track": "Be Here In The Morning - A COLORS SHOW"
    },
    "4872072918057200277": {
        "artist": "Pantera",
        "track": "Primal Concrete Sledge"
    },
    "4878178598431621507": {
        "artist": "Daniele Sepe Und Rote Jazz Fraktion",
        "track": "Let your past live"
    },
    "4941375498029379923": {
        "artist": "DakhaBrakha",
        "track": "Torokh"
    },
    "4967293643296939658": {
        "artist": "James Brown",
        "track": "Just You and Me, Darling"
    },
    "5079199835394175199": {
        "artist": "Slayer",
        "track": "Dead Skin Mask"
    },
    "5115970591633319308": {
        "artist": "Daniele Sepe Und Rote Jazz Fraktion",
        "track": "Guzzi Falcone"
    },
    "5155742650687015358": {
        "artist": "Sir Woman",
        "track": "Highroad"
    },
    "5232914401395848619": {
        "artist": "Sumac Dub",
        "track": "Le Jardin de Lucy"
    },
    "5268429909986590430": {
        "artist": "Dojo Cuts",
        "track": "If My Love Was Enough (feat. Natalie Slade)"
    },
    "5277852101292460317": {
        "artist": "Daniele Sepe Und Rote Jazz Fraktion",
        "track": "Come in coma"
    },
    "5374838708588259631": {
        "artist": "James Brown",
        "track": "Soulful Christmas"
    },
    "5402226374404559726": {
        "artist": "Marcello Colasurdo",
        "track": "Cilentane"
    },
    "5410894115530900361": {
        "artist": "Marcello Colasurdo",
        "track": "Catarina"
    },
    "5442632686005551060": {
        "artist": "Sangennarobar",
        "track": "Scetate Vajo' (Sangennarobar Cumbia remix)"
    },
    "5517032570978013857": {
        "artist": "Vinicio Capossela",
        "track": "Orfani ora"
    },
    "5667068288294962580": {
        "artist": "Nate Dogg",
        "track": "Nobody Does It Better"
    },
    "5674102894950369113": {
        "artist": "Tina Turner",
        "track": "The Best"
    },
    "5691154610324878693": {
        "artist": "Daniele Sepe Und Rote Jazz Fraktion",
        "track": "Radisol"
    },
    "5707616879659585178": {
        "artist": "Bootsy Collins",
        "track": "The Power of The One"
    },
    "5768272403704829779": {
        "artist": "Don Cherry",
        "track": "Chenrezig"
    },
    "5790814735760075666": {
        "artist": "Eda Marì",
        "track": "Male"
    },
    "5853729601249087149": {
        "artist": "Don Cherry",
        "track": "Nana's Solo"
    },
    "5932424808880854211": {
        "artist": "Radiodervish",
        "track": "All My Will"
    },
    "5956652638559735630": {
        "artist": "Sumac Dub",
        "track": "Intro"
    },
    "5958612859682307722": {
        "artist": "dumama + kechou",
        "track": "khala zome"
    },
    "6028251523554112299": {
        "artist": "Alain Goraguer",
        "track": "01 - Gogo's Goggles"
    },
    "6035004397751365377": {
        "artist": "Dojo Cuts",
        "track": "Falling In Love Again"
    },
    "6035076132446757155": {
        "artist": "Mitsoura",
        "track": "Rumelaj"
    },
    "6049689384545338164": {
        "artist": "Martha Reeves And The Vandellas",
        "track": "Heatwave - Re-Recording (By Original Artist)"
    },
    "6050737042959182083": {
        "artist": "Metallica",
        "track": "Fade to Black"
    },
    "6090104869943822606": {
        "artist": "The Dip",
        "track": "Atlas"
    },
    "6095834109166188783": {
        "artist": "Lo Stato Sociale",
        "track": "Mi sono rotto il cazzo"
    },
    "6098998146885409535": {
        "artist": "Sumac Dub",
        "track": "Tatooine Jam"
    },
    "6170929702999871204": {
        "artist": "The Rolling Stones",
        "track": "(I Can't Get No) Satisfaction"
    },
    "6220685809683573722": {
        "artist": "C.S.I.",
        "track": "Forma E Sostanza"
    },
    "6224341758259309784": {
        "artist": "Fear Factory",
        "track": "Replica"
    },
    "6227293862552409048": {
        "artist": "Vinicio Capossela",
        "track": "Dall'altra parte della sera"
    },
    "6296995903072482851": {
        "artist": "Pantera",
        "track": "Clash With Reality"
    },
    "6328620900245302230": {
        "artist": "Machine Head",
        "track": "Davidian"
    },
    "6385397630051831108": {
        "artist": "The Rolling Stones",
        "track": "It's Only Rock'n'Roll (But I Like It)"
    },
    "6483272313090812496": {
        "artist": "Vinicio Capossela",
        "track": "Con una rosa"
    },
    "6516385084444055659": {
        "artist": "Khruangbin",
        "track": "Time (You and I)"
    },
    "6525744746681785076": {
        "artist": "The Alan Parsons Project",
        "track": "Eye in the Sky"
    },
    "6672436359463040599": {
        "artist": "Creedence Clearwater Revival",
        "track": "Fortunate Son"
    },
    "6687865553320910611": {
        "artist": "Radiodervish",
        "track": "Rosa di turi"
    },
    "6691722203806317863": {
        "artist": "The Rolling Stones",
        "track": "Can't You Hear Me Knocking"
    },
    "6719017438403197463": {
        "artist": "DakhaBrakha",
        "track": "Sonnet"
    },
    "6782458654484039619": {
        "artist": "Snoop Dogg",
        "track": "Gin And Juice (Feat. Dat Nigga Daz)"
    },
    "6851357657623948698": {
        "artist": "Green Day",
        "track": "21 Guns"
    },
    "6906747390258310778": {
        "artist": "The Police",
        "track": "Walking on the Moon"
    },
    "6995007716013919048": {
        "artist": "Metallica",
        "track": "Master of Puppets"
    },
    "7022161013907398966": {
        "artist": "The Brooks",
        "track": "Gameplay"
    },
    "7049886989478812548": {
        "artist": "Bon Jovi",
        "track": "Runaway"
    },
    "7068728633930504259": {
        "artist": "Emre Gültekin & Vardan Hovanissian",
        "track": "Yerazov Archik"
    },
    "7119377926022499782": {
        "artist": "Daniele Sepe Und Rote Jazz Fraktion",
        "track": "Sintonia N.1 In Do Mag  \"Il Pendolo\""
    },
    "7124135647132038270": {
        "artist": "Jean Tonique",
        "track": "Flawless"
    },
    "7140986903407318910": {
        "artist": "Nickelback",
        "track": "Burn It To The Ground"
    },
    "7208031431908623837": {
        "artist": "Kiss",
        "track": "Rock And Roll All Nite"
    },
    "7288270100586414587": {
        "artist": "Sheriff",
        "track": "When I'm With You"
    },
    "7331788373824194059": {
        "artist": "Led Zeppelin",
        "track": "Good Times Bad Times"
    },
    "7350911212430654520": {
        "artist": "Jess Willard",
        "track": "Honkytonk Hardwood Floor"
    },
    "7369671193478508551": {
        "artist": "BLOODY VINYL",
        "track": "ALTALENE (feat. Mara Sattei  Coez)"
    },
    "7415903508620164973": {
        "artist": "SCHROOTHOOP",
        "track": "Sluikstort"
    },
    "7445067780489057300": {
        "artist": "Fabi Silvestri Gazzè",
        "track": "L'amore non esiste"
    },
    "7509980402027379526": {
        "artist": "Léo De Hurlevent",
        "track": "Vibrer"
    },
    "7562163250579260153": {
        "artist": "James Brown",
        "track": "Say It Loud, I'm Black and I'm Proud"
    },
    "7564342143230761803": {
        "artist": "Bon Jovi",
        "track": "Always"
    },
    "7578805869058879350": {
        "artist": "Mitsoura",
        "track": "Sat Bhayan"
    },
    "7595297837956249551": {
        "artist": "Janis Joplin",
        "track": "Piece of My Heart"
    },
    "7684426879445229520": {
        "artist": "DakhaBrakha",
        "track": "Alambari"
    },
    "7690559408827681732": {
        "artist": "Vinicio Capossela",
        "track": "Vetri appannati d'america"
    },
    "7768276722199871690": {
        "artist": "Alain Goraguer",
        "track": "08 - You Are Too Beautiful"
    },
    "7772245276077046569": {
        "artist": "Alain Goraguer",
        "track": "12 - The Nearness of You"
    },
    "7776243828621505891": {
        "artist": "Black Veil Brides",
        "track": "In The End"
    },
    "7840524489016445628": {
        "artist": "Thee Sinseers",
        "track": "Seems Like"
    },
    "7880695533973714708": {
        "artist": "Carpenters",
        "track": "Yesterday Once More"
    },
    "7924775997587104678": {
        "artist": "DakhaBrakha",
        "track": "Im tanzen liebe"
    },
    "7931802819323256798": {
        "artist": "Tess Henley",
        "track": "Same Girl"
    },
    "7952428022774463900": {
        "artist": "Breakbot",
        "track": "Baby I'm Yours"
    },
    "8054708987714122746": {
        "artist": "Nate Dogg",
        "track": "Cool (feat. Butch Cassidy, Kokane  Nate Dogg)"
    },
    "8085715542016288574": {
        "artist": "James Brown",
        "track": "I Need Your Love So Bad"
    },
    "8099890519402933635": {
        "artist": "SCHROOTHOOP",
        "track": "Obsolescence Programmée"
    },
    "8200766239322253752": {
        "artist": "Linkin Park",
        "track": "Somewhere I Belong"
    },
    "8227244875423440333": {
        "artist": "Franco Battiato",
        "track": "La Convenzione (1997 Version)"
    },
    "8245780479933520500": {
        "artist": "Jimi Hendrix",
        "track": "Red House"
    },
    "8261503288369975625": {
        "artist": "Alain Goraguer",
        "track": "16 - Star Eyes"
    },
    "8277644425798297869": {
        "artist": "Metallica",
        "track": "One"
    },
    "8393536309355418121": {
        "artist": "Sly & The Family Stone",
        "track": "Underdog"
    },
    "8402733123897430490": {
        "artist": "ZZ Top",
        "track": "Gimme All Your Lovin'"
    },
    "8478382140887147162": {
        "artist": "Carly Simon",
        "track": "Why"
    },
    "8499087899451884407": {
        "artist": "Curtis Mayfield",
        "track": "Move On Up"
    },
    "8508480461909685343": {
        "artist": "Lasperanza",
        "track": "It Should Have Been You"
    },
    "8508501444249238668": {
        "artist": "Juri Camisasca",
        "track": "Il Regno Dell'Eden, 1° Parte"
    },
    "8551349361085799681": {
        "artist": "Chris Isaak",
        "track": "Blue Hotel"
    },
    "8587728750713603481": {
        "artist": "Radiodervish",
        "track": "Belzebù"
    },
    "8590018083033262549": {
        "artist": "The Cars",
        "track": "Drive"
    },
    "8620247276533806356": {
        "artist": "Neffa",
        "track": "Aspettando Il Sole"
    },
    "8657691946130710074": {
        "artist": "Benjamin Lew",
        "track": "Joyeux Regrets Imprécis"
    },
    "8695888788823596745": {
        "artist": "Benjamin Lew",
        "track": "Le Personnage Principal Est Un Peuple Isolé"
    },
    "8766383538689576773": {
        "artist": "New York Dolls",
        "track": "Looking for a Kiss"
    },
    "8808625646520309967": {
        "artist": "Daniele Sepe Und Rote Jazz Fraktion",
        "track": "Hasta siempre"
    },
    "8909858475121105109": {
        "artist": "Pantera",
        "track": "Psycho Holiday"
    },
    "8923663837446950101": {
        "artist": "Sweet",
        "track": "The Ballroom Blitz"
    },
    "8964930747564854583": {
        "artist": "Mitsoura",
        "track": "Dura Dura Dura"
    },
    "8965211943886344977": {
        "artist": "Audioslave",
        "track": "Show Me How To Live"
    },
    "8984846809955919276": {
        "artist": "Womack  Womack",
        "track": "Teardrops"
    },
    "8990910711465261321": {
        "artist": "James Brown",
        "track": "I Don't Mind"
    },
    "9004109659078361545": {
        "artist": "Derek and the Dominos",
        "track": "Layla"
    },
    "9076183958448583344": {
        "artist": "Osage Tribe",
        "track": "Crazy Horse"
    },
    "9152491806174762293": {
        "artist": "SCHROOTHOOP",
        "track": "Magnetron"
    },
    "9161713330073407060": {
        "artist": "Emre Gültekin & Vardan Hovanissian",
        "track": "Dzun Giker"
    },
    "9183118324203535961": {
        "artist": "Don Cherry",
        "track": "Dissolution"
    }
}